<?xml version="1.0" encoding="UTF-8" ?>
<!DOCTYPE mapper PUBLIC "-//mybatis.org//DTD Mapper 3.0//EN" "http://mybatis.org/dtd/mybatis-3-mapper.dtd" >
<mapper namespace="com.soecode.lyf.dao.OrderMapper" >
  <resultMap id="BaseResultMap" type="com.soecode.lyf.entity.Order" >
    <!--
      WARNING - @mbggenerated
      This element is automatically generated by MyBatis Generator, do not modify.
    -->
    <id column="orderId" property="orderid" jdbcType="VARCHAR" />
    <result column="wxopenId" property="wxopenid" jdbcType="VARCHAR" />
    <result column="senderName" property="sendername" jdbcType="VARCHAR" />
    <result column="senderPhone" property="senderphone" jdbcType="INTEGER" />
    <result column="senderAddressId" property="senderaddressid" jdbcType="INTEGER" />
    <result column="recipientName" property="recipientname" jdbcType="VARCHAR" />
    <result column="recipientPhone" property="recipientphone" jdbcType="INTEGER" />
    <result column="recipientAddressId" property="recipientaddressid" jdbcType="INTEGER" />
    <result column="weight" property="weight" jdbcType="INTEGER" />
    <result column="amount" property="amount" jdbcType="DECIMAL" />
    <result column="status" property="status" jdbcType="INTEGER" />
    <result column="username" property="username" jdbcType="VARCHAR" />
    <result column="isable" property="isable" jdbcType="INTEGER" />
  </resultMap>
  <resultMap id="ResultMapWithBLOBs" type="com.soecode.lyf.entity.OrderWithBLOBs" extends="BaseResultMap" >
    <!--
      WARNING - @mbggenerated
      This element is automatically generated by MyBatis Generator, do not modify.
    -->
    <result column="senderAddressDetail" property="senderaddressdetail" jdbcType="LONGVARCHAR" />
    <result column="recipientAddressDetail" property="recipientaddressdetail" jdbcType="LONGVARCHAR" />
  </resultMap>
  <sql id="Base_Column_List" >
    <!--
      WARNING - @mbggenerated
      This element is automatically generated by MyBatis Generator, do not modify.
    -->
    orderId, wxopenId, senderName, senderPhone, senderAddressId, recipientName, recipientPhone, 
    recipientAddressId, weight, amount, status, username, isable
  </sql>
  <sql id="Blob_Column_List" >
    <!--
      WARNING - @mbggenerated
      This element is automatically generated by MyBatis Generator, do not modify.
    -->
    senderAddressDetail, recipientAddressDetail
  </sql>
  <select id="selectByPrimaryKey" resultMap="ResultMapWithBLOBs" parameterType="java.lang.String" >
    <!--
      WARNING - @mbggenerated
      This element is automatically generated by MyBatis Generator, do not modify.
    -->
    select 
    <include refid="Base_Column_List" />
    ,
    <include refid="Blob_Column_List" />
    from order
    where orderId = #{orderid,jdbcType=VARCHAR}
  </select>
  <delete id="deleteByPrimaryKey" parameterType="java.lang.String" >
    <!--
      WARNING - @mbggenerated
      This element is automatically generated by MyBatis Generator, do not modify.
    -->
    delete from order
    where orderId = #{orderid,jdbcType=VARCHAR}
  </delete>
  <insert id="insert" parameterType="com.soecode.lyf.entity.OrderWithBLOBs" >
    <!--
      WARNING - @mbggenerated
      This element is automatically generated by MyBatis Generator, do not modify.
    -->
    insert into order (orderId, wxopenId, senderName, 
      senderPhone, senderAddressId, recipientName, 
      recipientPhone, recipientAddressId, weight, 
      amount, status, username, 
      isable, senderAddressDetail, recipientAddressDetail
      )
    values (#{orderid,jdbcType=VARCHAR}, #{wxopenid,jdbcType=VARCHAR}, #{sendername,jdbcType=VARCHAR}, 
      #{senderphone,jdbcType=INTEGER}, #{senderaddressid,jdbcType=INTEGER}, #{recipientname,jdbcType=VARCHAR}, 
      #{recipientphone,jdbcType=INTEGER}, #{recipientaddressid,jdbcType=INTEGER}, #{weight,jdbcType=INTEGER}, 
      #{amount,jdbcType=DECIMAL}, #{status,jdbcType=INTEGER}, #{username,jdbcType=VARCHAR}, 
      #{isable,jdbcType=INTEGER}, #{senderaddressdetail,jdbcType=LONGVARCHAR}, #{recipientaddressdetail,jdbcType=LONGVARCHAR}
      )
  </insert>
  <insert id="insertSelective" parameterType="com.soecode.lyf.entity.OrderWithBLOBs" >
    <!--
      WARNING - @mbggenerated
      This element is automatically generated by MyBatis Generator, do not modify.
    -->
    insert into order
    <trim prefix="(" suffix=")" suffixOverrides="," >
      <if test="orderid != null" >
        orderId,
      </if>
      <if test="wxopenid != null" >
        wxopenId,
      </if>
      <if test="sendername != null" >
        senderName,
      </if>
      <if test="senderphone != null" >
        senderPhone,
      </if>
      <if test="senderaddressid != null" >
        senderAddressId,
      </if>
      <if test="recipientname != null" >
        recipientName,
      </if>
      <if test="recipientphone != null" >
        recipientPhone,
      </if>
      <if test="recipientaddressid != null" >
        recipientAddressId,
      </if>
      <if test="weight != null" >
        weight,
      </if>
      <if test="amount != null" >
        amount,
      </if>
      <if test="status != null" >
        status,
      </if>
      <if test="username != null" >
        username,
      </if>
      <if test="isable != null" >
        isable,
      </if>
      <if test="senderaddressdetail != null" >
        senderAddressDetail,
      </if>
      <if test="recipientaddressdetail != null" >
        recipientAddressDetail,
      </if>
    </trim>
    <trim prefix="values (" suffix=")" suffixOverrides="," >
      <if test="orderid != null" >
        #{orderid,jdbcType=VARCHAR},
      </if>
      <if test="wxopenid != null" >
        #{wxopenid,jdbcType=VARCHAR},
      </if>
      <if test="sendername != null" >
        #{sendername,jdbcType=VARCHAR},
      </if>
      <if test="senderphone != null" >
        #{senderphone,jdbcType=INTEGER},
      </if>
      <if test="senderaddressid != null" >
        #{senderaddressid,jdbcType=INTEGER},
      </if>
      <if test="recipientname != null" >
        #{recipientname,jdbcType=VARCHAR},
      </if>
      <if test="recipientphone != null" >
        #{recipientphone,jdbcType=INTEGER},
      </if>
      <if test="recipientaddressid != null" >
        #{recipientaddressid,jdbcType=INTEGER},
      </if>
      <if test="weight != null" >
        #{weight,jdbcType=INTEGER},
      </if>
      <if test="amount != null" >
        #{amount,jdbcType=DECIMAL},
      </if>
      <if test="status != null" >
        #{status,jdbcType=INTEGER},
      </if>
      <if test="username != null" >
        #{username,jdbcType=VARCHAR},
      </if>
      <if test="isable != null" >
        #{isable,jdbcType=INTEGER},
      </if>
      <if test="senderaddressdetail != null" >
        #{senderaddressdetail,jdbcType=LONGVARCHAR},
      </if>
      <if test="recipientaddressdetail != null" >
        #{recipientaddressdetail,jdbcType=LONGVARCHAR},
      </if>
    </trim>
  </insert>
  <update id="updateByPrimaryKeySelective" parameterType="com.soecode.lyf.entity.OrderWithBLOBs" >
    <!--
      WARNING - @mbggenerated
      This element is automatically generated by MyBatis Generator, do not modify.
    -->
    update order
    <set >
      <if test="wxopenid != null" >
        wxopenId = #{wxopenid,jdbcType=VARCHAR},
      </if>
      <if test="sendername != null" >
        senderName = #{sendername,jdbcType=VARCHAR},
      </if>
      <if test="senderphone != null" >
        senderPhone = #{senderphone,jdbcType=INTEGER},
      </if>
      <if test="senderaddressid != null" >
        senderAddressId = #{senderaddressid,jdbcType=INTEGER},
      </if>
      <if test="recipientname != null" >
        recipientName = #{recipientname,jdbcType=VARCHAR},
      </if>
      <if test="recipientphone != null" >
        recipientPhone = #{recipientphone,jdbcType=INTEGER},
      </if>
      <if test="recipientaddressid != null" >
        recipientAddressId = #{recipientaddressid,jdbcType=INTEGER},
      </if>
      <if test="weight != null" >
        weight = #{weight,jdbcType=INTEGER},
      </if>
      <if test="amount != null" >
        amount = #{amount,jdbcType=DECIMAL},
      </if>
      <if test="status != null" >
        status = #{status,jdbcType=INTEGER},
      </if>
      <if test="username != null" >
        username = #{username,jdbcType=VARCHAR},
      </if>
      <if test="isable != null" >
        isable = #{isable,jdbcType=INTEGER},
      </if>
      <if test="senderaddressdetail != null" >
        senderAddressDetail = #{senderaddressdetail,jdbcType=LONGVARCHAR},
      </if>
      <if test="recipientaddressdetail != null" >
        recipientAddressDetail = #{recipientaddressdetail,jdbcType=LONGVARCHAR},
      </if>
    </set>
    where orderId = #{orderid,jdbcType=VARCHAR}
  </update>
  <update id="updateByPrimaryKeyWithBLOBs" parameterType="com.soecode.lyf.entity.OrderWithBLOBs" >
    <!--
      WARNING - @mbggenerated
      This element is automatically generated by MyBatis Generator, do not modify.
    -->
    update order
    set wxopenId = #{wxopenid,jdbcType=VARCHAR},
      senderName = #{sendername,jdbcType=VARCHAR},
      senderPhone = #{senderphone,jdbcType=INTEGER},
      senderAddressId = #{senderaddressid,jdbcType=INTEGER},
      recipientName = #{recipientname,jdbcType=VARCHAR},
      recipientPhone = #{recipientphone,jdbcType=INTEGER},
      recipientAddressId = #{recipientaddressid,jdbcType=INTEGER},
      weight = #{weight,jdbcType=INTEGER},
      amount = #{amount,jdbcType=DECIMAL},
      status = #{status,jdbcType=INTEGER},
      username = #{username,jdbcType=VARCHAR},
      isable = #{isable,jdbcType=INTEGER},
      senderAddressDetail = #{senderaddressdetail,jdbcType=LONGVARCHAR},
      recipientAddressDetail = #{recipientaddressdetail,jdbcType=LONGVARCHAR}
    where orderId = #{orderid,jdbcType=VARCHAR}
  </update>
  <update id="updateByPrimaryKey" parameterType="com.soecode.lyf.entity.Order" >
    <!--
      WARNING - @mbggenerated
      This element is automatically generated by MyBatis Generator, do not modify.
    -->
    update order
    set wxopenId = #{wxopenid,jdbcType=VARCHAR},
      senderName = #{sendername,jdbcType=VARCHAR},
      senderPhone = #{senderphone,jdbcType=INTEGER},
      senderAddressId = #{senderaddressid,jdbcType=INTEGER},
      recipientName = #{recipientname,jdbcType=VARCHAR},
      recipientPhone = #{recipientphone,jdbcType=INTEGER},
      recipientAddressId = #{recipientaddressid,jdbcType=INTEGER},
      weight = #{weight,jdbcType=INTEGER},
      amount = #{amount,jdbcType=DECIMAL},
      status = #{status,jdbcType=INTEGER},
      username = #{username,jdbcType=VARCHAR},
      isable = #{isable,jdbcType=INTEGER}
    where orderId = #{orderid,jdbcType=VARCHAR}
  </update>
</mapper>